parserrtm/__init__.py
parserrtm/input.py
parserrtm/longwave.py
parserrtm/runner.py
parserrtm/shortwave.py
parserrtm-0.1.1.dist-info/licenses/LICENSE
parserrtm-0.1.1.dist-info/METADATA
parserrtm-0.1.1.dist-info/WHEEL
parserrtm-0.1.1.dist-info/top_level.txt
parserrtm-0.1.1.dist-info/RECORD
