Metadata-Version: 2.4
Name: parserrtm
Version: 0.1.1
Summary: Fully-featured Python interface for rapid radiative transfer model (RRTM)
Author: Leah Bertrand
License-Expression: GPL-3.0
Project-URL: Homepage, https://github.com/bertrandclim/parserrtm
Project-URL: Issues, https://github.com/bertrandclim/parserrtm/issues
Classifier: Programming Language :: Python :: 3
Classifier: Operating System :: OS Independent
Requires-Python: >=3.9
License-File: LICENSE
Requires-Dist: pandas
Requires-Dist: xarray
Requires-Dist: fortranformat
Dynamic: license-file
